deepctl/__init__.py
deepctl/main.py
deepctl-0.1.10.dist-info/METADATA
deepctl-0.1.10.dist-info/WHEEL
deepctl-0.1.10.dist-info/entry_points.txt
deepctl-0.1.10.dist-info/top_level.txt
deepctl-0.1.10.dist-info/RECORD
