Metadata-Version: 2.4
Name: deepctl
Version: 0.1.10
Summary: Official Deepgram CLI for speech recognition and audio intelligence
Author-email: Deepgram <devrel@deepgram.com>
Maintainer-email: Deepgram <devrel@deepgram.com>
License-Expression: MIT
Project-URL: Homepage, https://github.com/deepgram/cli
Project-URL: Documentation, https://developers.deepgram.com/docs/cli
Project-URL: Repository, https://github.com/deepgram/cli
Project-URL: Bug Tracker, https://github.com/deepgram/cli/issues
Project-URL: Community, https://discord.gg/deepgram
Keywords: deepgram,speech,recognition,transcription,audio,cli
Classifier: Development Status :: 3 - Alpha
Classifier: Intended Audience :: Developers
Classifier: Programming Language :: Python :: 3
Classifier: Programming Language :: Python :: 3.10
Classifier: Programming Language :: Python :: 3.11
Classifier: Programming Language :: Python :: 3.12
Classifier: Topic :: Software Development :: Libraries :: Python Modules
Classifier: Topic :: Multimedia :: Sound/Audio :: Speech
Classifier: Topic :: Scientific/Engineering :: Artificial Intelligence
Requires-Python: >=3.10
Requires-Dist: click>=8.0.0
Requires-Dist: deepgram-sdk>=3.0.0
Requires-Dist: deepctl-core>=0.1.10
Requires-Dist: deepctl-cmd-login>=0.1.10
Requires-Dist: deepctl-cmd-projects>=0.1.10
Requires-Dist: deepctl-cmd-transcribe>=0.1.10
Requires-Dist: deepctl-cmd-usage>=0.1.10
Requires-Dist: deepctl-cmd-mcp>=0.1.10
Requires-Dist: deepctl-cmd-debug>=0.1.10
Requires-Dist: deepctl-cmd-debug-browser>=0.1.10
Requires-Dist: deepctl-cmd-debug-network>=0.1.10
Requires-Dist: deepctl-cmd-debug-audio>=0.1.10
Requires-Dist: deepctl-cmd-update>=0.1.10
Requires-Dist: deepctl-cmd-plugin>=0.1.10
Requires-Dist: deepctl-shared-utils>=0.1.10
Requires-Dist: pydantic>=2.0.0
Requires-Dist: rich>=13.0.0
Requires-Dist: httpx>=0.24.0
Requires-Dist: requests<3.0,>=2.31
Requires-Dist: pyjwt>=2.8.0
Requires-Dist: keyring>=24.0.0
Requires-Dist: pyyaml>=6.0.0
Requires-Dist: typer>=0.9.0
Requires-Dist: platformdirs>=3.0.0
Provides-Extra: dev
Requires-Dist: pytest>=7.0.0; extra == "dev"
Requires-Dist: pytest-asyncio>=0.21.0; extra == "dev"
Requires-Dist: pytest-cov>=4.0.0; extra == "dev"
Requires-Dist: pytest-mock>=3.10.0; extra == "dev"
Requires-Dist: responses>=0.23.0; extra == "dev"
Requires-Dist: black>=23.0.0; extra == "dev"
Requires-Dist: ruff>=0.8.0; extra == "dev"
Requires-Dist: mypy>=1.0.0; extra == "dev"
Requires-Dist: types-PyYAML>=6.0.0; extra == "dev"
Requires-Dist: types-requests>=2.31.0; extra == "dev"
Requires-Dist: pre-commit>=3.0.0; extra == "dev"
Requires-Dist: tox>=4.0.0; extra == "dev"
Requires-Dist: twine>=4.0.0; extra == "dev"
Requires-Dist: build>=0.10.0; extra == "dev"
